gnotas/__init__.py
gnotas/gestor.py
gnotas/main.py
gnotas/notas.py
gnotas-0.1.0.dist-info/METADATA
gnotas-0.1.0.dist-info/WHEEL
gnotas-0.1.0.dist-info/top_level.txt
gnotas-0.1.0.dist-info/RECORD
