Metadata-Version: 2.4
Name: gnotas
Version: 0.1.0
Summary: Un gestor de notas simple
Author: Sir Pixel
Dynamic: author
Dynamic: description
Dynamic: description-content-type
Dynamic: summary
